{"cameraMode":{"drawMode":0,"name":"Shaded","section":"Shading Mode"},"sceneLighting":true,"audioPlay":false,"sceneViewState":{"m_AlwaysRefresh":false,"showFog":true,"showSkybox":true,"showFlares":true,"showImageEffects":true,"showParticleSystems":true,"showVisualEffectGraphs":true,"m_FxEnabled":true},"in2DMode":false,"pivot":{"x":52.083885192871097,"y":1.5461935997009278,"z":35.261207580566409},"rotation":{"x":0.029435230419039727,"y":-0.902573823928833,"z":0.06269487738609314,"w":0.42510882019996645},"size":1.5929466485977173,"orthographic":false}